{
    "all": {
        "include": {
            "all": [
                "alsa-firmware",
                "btop",
                "coolercontrol",
                "coolercontrold",
                "cliphist",
                "easyeffects",
                "fastfetch",
                "ffmpeg-free",
                "flatpak",
                "flatpak-spawn",
                "fzf",
                "greetd",
                "heif-pixbuf-loader",
                "hyprdim",
                "hypridle",
                "hyprland",
                "hyprland-autoname-workspaces",
                "hyprland-contrib",
                "hyprland-plugins",
                "hyprpolkitagent",
                "hyprsunset",
                "just",
                "lact",
                "mozilla-openh264",
                "nautilus",
                "noopenh264",
                "neovim",
                "openh264",
                "solaar-udev",
                "steam-devices",
                "swww",
                "tuigreet",
                "waybar-git",
                "wl-clipboard",
                "wlogout",
                "xdg-desktop-portal-hyprland",
                "zsh"
            ]
        },
        "exclude": {
            "all": [
                "usbmuxd"
            ]
        },
        "swap": {
            "all": {
                "kitty": "ghostty"
            }
        }
    }
}
